README.md
setup.cfg
setup.py
cartogrammetry/__init__.py
cartogrammetry/cartogram.py
cartogrammetry/create.py
cartogrammetry/solve.py
cartogrammetry.egg-info/PKG-INFO
cartogrammetry.egg-info/SOURCES.txt
cartogrammetry.egg-info/dependency_links.txt
cartogrammetry.egg-info/requires.txt
cartogrammetry.egg-info/top_level.txt