Metadata-Version: 2.1
Name: cartogrammetry
Version: 0.0.4
Summary: A Python package for creating block or circle style cartograms.
Home-page: https://github.com/ivodeliefde/cartogrammetry
Author: Ivo de Liefde
Author-email: ivodeliefde@gmail.com
License: MIT
Platform: UNKNOWN
Classifier: Development Status :: 3 - Alpha
Classifier: Intended Audience :: Developers
Classifier: Programming Language :: Python :: 3
Classifier: License :: OSI Approved :: MIT License
Classifier: Operating System :: OS Independent
Requires-Python: >=3.7
